{"CONFIG":[{"ruta":"https://sparkly-marshmallow-d966ed.netlify.app/galeria/"}],"FLAG":[],"CADETE":[{"imagen":"cadete_foto_001.jpg"},{"imagen":"cadete_foto_002.JPG"},{"imagen":"cadete_foto_003.jpg"},{"imagen":"cadete_foto_004.jpg"},{"imagen":"cadete_foto_005.jpg"},{"imagen":"cadete_foto_006.jpg"},{"imagen":"cadete_foto_007.jpg"},{"imagen":"cadete_foto_008.jpg"},{"imagen":"cadete_foto_009.jpg"},{"imagen":"cadete_foto_010.jpg"},{"imagen":"cadete_foto_011.jpg"},{"imagen":"cadete_foto_012.jpg"},{"imagen":"cadete_foto_013.jpg"},{"imagen":"cadete_foto_014.jpg"},{"imagen":"cadete_foto_015.jpg"},{"imagen":"cadete_foto_016.jpg"}],"JUNIOR":[],"SRFEMENINO":[{"imagen":"srfemenino_foto_001.jpg"},{"imagen":"srfemenino_foto_002.jpg"},{"imagen":"srfemenino_foto_003.jpg"},{"imagen":"srfemenino_foto_004.jpg"},{"imagen":"srfemenino_foto_005.jpg"},{"imagen":"srfemenino_foto_006.jpg"},{"imagen":"srfemenino_foto_007.jpg"},{"imagen":"srfemenino_foto_008.jpg"},{"imagen":"srfemenino_foto_009.jpg"},{"imagen":"srfemenino_foto_010.jpg"},{"imagen":"srfemenino_foto_011.jpg"}],"SRMASCULINO":[]}
